installed_browsers/__init__.py
installed_browsers/common.py
installed_browsers/linux.py
installed_browsers/mac.py
installed_browsers/windows.py
installed_browsers-0.1.5.dist-info/LICENSE
installed_browsers-0.1.5.dist-info/METADATA
installed_browsers-0.1.5.dist-info/WHEEL
installed_browsers-0.1.5.dist-info/RECORD
