Metadata-Version: 2.3
Name: installed-browsers
Version: 0.1.5
Summary: Python library to check installed browsers
License: MIT
Author: undeflorate
Author-email: swanslayer@gmail.com
Requires-Python: >=3.10,<4.0
Classifier: Development Status :: 5 - Production/Stable
Classifier: License :: OSI Approved :: MIT License
Classifier: Programming Language :: Python :: 3
Classifier: Programming Language :: Python :: 3.10
Classifier: Programming Language :: Python :: 3.11
Classifier: Programming Language :: Python :: 3.12
Classifier: Programming Language :: Python :: 3.13
Classifier: Topic :: Internet :: WWW/HTTP :: Browsers
Classifier: Topic :: Software Development :: Libraries :: Python Modules
Requires-Dist: pywin32 (>=303,<311) ; sys_platform == "win32"
Requires-Dist: pyxdg (>=0.27,<0.29) ; sys_platform == "linux"
Project-URL: Repository, https://github.com/undeflorate/installed_browsers
